mpltoolbox/__init__.py
mpltoolbox/ellipses.py
mpltoolbox/event.py
mpltoolbox/hspans.py
mpltoolbox/lines.py
mpltoolbox/patch.py
mpltoolbox/points.py
mpltoolbox/polygons.py
mpltoolbox/py.typed
mpltoolbox/rectangles.py
mpltoolbox/tool.py
mpltoolbox/utils.py
mpltoolbox/vspans.py
mpltoolbox-25.10.0.dist-info/licenses/LICENSE
mpltoolbox-25.10.0.dist-info/METADATA
mpltoolbox-25.10.0.dist-info/WHEEL
mpltoolbox-25.10.0.dist-info/top_level.txt
mpltoolbox-25.10.0.dist-info/RECORD
