Metadata-Version: 2.4
Name: mpltoolbox
Version: 25.10.0
Summary: Interactive tools for Matplotlib
Author: Scipp contributors
License-Expression: BSD-3-Clause
Project-URL: Bug Tracker, https://github.com/scipp/mpltoolbox/issues
Project-URL: Documentation, https://scipp.github.io/mpltoolbox
Project-URL: Source, https://github.com/scipp/mpltoolbox
Classifier: Intended Audience :: Science/Research
Classifier: Natural Language :: English
Classifier: Operating System :: OS Independent
Classifier: Programming Language :: Python :: 3
Classifier: Programming Language :: Python :: 3 :: Only
Classifier: Programming Language :: Python :: 3.11
Classifier: Programming Language :: Python :: 3.12
Classifier: Programming Language :: Python :: 3.13
Classifier: Topic :: Scientific/Engineering
Classifier: Typing :: Typed
Requires-Python: >=3.11
License-File: LICENSE
Requires-Dist: matplotlib
Provides-Extra: test
Requires-Dist: pytest; extra == "test"
Requires-Dist: ipympl; extra == "test"
Dynamic: license-file
